threlog/__init__.py
threlog-0.1.0.dist-info/LICENSE
threlog-0.1.0.dist-info/METADATA
threlog-0.1.0.dist-info/WHEEL
threlog-0.1.0.dist-info/top_level.txt
threlog-0.1.0.dist-info/RECORD
